CHANGELOG.rst
openldap_config_parser/__init__.py
openldap_config_parser/command.py
openldap_config_parser/config.py
openldap_config_parser/database.py
openldap_config_parser/exceptions.py
openldap_config_parser/parser.py
openldap_config_parser/py.typed
openldap_config_parser-1.0.4.dist-info/entry_points.txt
openldap_config_parser-1.0.4.dist-info/LICENSE
openldap_config_parser-1.0.4.dist-info/WHEEL
openldap_config_parser-1.0.4.dist-info/METADATA
openldap_config_parser-1.0.4.dist-info/RECORD
