Metadata-Version: 2.1
Name: openldap-config-parser
Version: 1.0.4
Summary: slapd.conf parser for OpenLDAP
Home-page: https://github.com/mypaceshun/openldap-config-parser
License: MIT
Author: KAWAI Shun
Author-email: shun@osstech.co.jp
Requires-Python: >=3.8,<4.0
Classifier: License :: OSI Approved :: MIT License
Classifier: Programming Language :: Python :: 3
Classifier: Programming Language :: Python :: 3.10
Classifier: Programming Language :: Python :: 3.8
Classifier: Programming Language :: Python :: 3.9
Requires-Dist: click (>=8.1.2,<9.0.0)
Requires-Dist: rich (>=12.2.0,<13.0.0)
Project-URL: Documentation, https://openldap-config-parser.readthedocs.io
Project-URL: Repository, https://github.com/mypaceshun/openldap-config-parser
